umaru/__init__.py
umaru/__main__.py
umaru/umaru.py
umaru/umaru_keyboard.py
umaru-1.0.dist-info/LICENSE
umaru-1.0.dist-info/METADATA
umaru-1.0.dist-info/WHEEL
umaru-1.0.dist-info/entry_points.txt
umaru-1.0.dist-info/RECORD
