Metadata-Version: 2.1
Name: umaru
Version: 1.0
Summary: A small Switch Pro Controller driver which lets you use your computer with it !
Home-page: https://github.com/Animenosekai/umaru
License: MIT
Keywords: animenosekai,umaru,console,switch,controller,pro controller,game controller,game
Author: Animenosekai
Author-email: animenosekai.mail@gmail.com
Maintainer: Animenosekai
Maintainer-email: animenosekai.mail@gmail.com
Requires-Python: >=3.7,<4.0
Classifier: Development Status :: 4 - Beta
Classifier: Environment :: Console
Classifier: Intended Audience :: End Users/Desktop
Classifier: License :: OSI Approved :: MIT License
Classifier: Operating System :: OS Independent
Classifier: Programming Language :: Python
Classifier: Programming Language :: Python :: 3
Classifier: Programming Language :: Python :: 3.7
Classifier: Programming Language :: Python :: 3.8
Classifier: Programming Language :: Python :: 3.9
Classifier: Programming Language :: Python :: 3.10
Classifier: Programming Language :: Python :: 3.11
Classifier: Topic :: System :: Hardware
Classifier: Typing :: Typed
Requires-Dist: hidapi (>=0.14.0,<0.15.0)
Requires-Dist: pynput (>=1.7.6,<2.0.0)
Requires-Dist: rich (>=13.5.1,<14.0.0)
Project-URL: Documentation, https://github.com/Animenosekai/umaru/blob/main/README.md
Project-URL: Issue Tracker, https://github.com/Animenosekai/umaru/issues
Project-URL: Repository, https://github.com/Animenosekai/umaru
